promptify/__init__.py
promptify/models/__init__.py
promptify/models/nlp/__init__.py
promptify/models/nlp/model.py
promptify/models/nlp/openai_model.py
promptify/models/nlp/utils/__init__.py
promptify/models/nlp/utils/bpe_encoder.py
promptify/models/nlp/utils/utils.py
promptify/models/tabular/__init__.py
promptify/models/vision/__init__.py
promptify/prompts/__init__.py
promptify/prompts/nlp/__init__.py
promptify/prompts/nlp/prompter.py
promptify/prompts/tabular/__init__.py
promptify/prompts/vision/__init__.py
promptify-0.1.0.dist-info/LICENSE
promptify-0.1.0.dist-info/METADATA
promptify-0.1.0.dist-info/WHEEL
promptify-0.1.0.dist-info/top_level.txt
promptify-0.1.0.dist-info/RECORD
