Metadata-Version: 2.1
Name: promptify
Version: 0.1.0
Summary: Use GPT or other prompt based models to get structured output
Home-page: https://github.com/promptslab/Promptify
Author: The promptslab team with the help of all our contributors (https://github.com/promptslab/Promptify/graphs/contributors)
License: Apache
Platform: UNKNOWN
Requires-Python: >=3.7.0
License-File: LICENSE
Requires-Dist: openai (==0.25.0)
Requires-Dist: regex (==2022.10.31)
Requires-Dist: appdirs (==1.4.4)
Requires-Dist: jinja2 (==2.11.3)
Provides-Extra: dev
Requires-Dist: black (==22.12.0) ; extra == 'dev'
Requires-Dist: isort (==5.11.4) ; extra == 'dev'
Requires-Dist: flake8 (==6.0.0) ; extra == 'dev'
